marionette_driver/__init__.py
marionette_driver/addons.py
marionette_driver/by.py
marionette_driver/date_time_value.py
marionette_driver/decorators.py
marionette_driver/errors.py
marionette_driver/expected.py
marionette_driver/geckoinstance.py
marionette_driver/keys.py
marionette_driver/localization.py
marionette_driver/marionette.py
marionette_driver/processhandler.py
marionette_driver/timeout.py
marionette_driver/transport.py
marionette_driver/wait.py
marionette_driver/webauthn.py
marionette_driver-3.5.0.dist-info/METADATA
marionette_driver-3.5.0.dist-info/WHEEL
marionette_driver-3.5.0.dist-info/top_level.txt
marionette_driver-3.5.0.dist-info/RECORD
